LICENSE
MANIFEST.in
README.md
setup.py
snmp_simulator/__init__.py
snmp_simulator/simulator.py
snmp_simulator.egg-info/PKG-INFO
snmp_simulator.egg-info/SOURCES.txt
snmp_simulator.egg-info/dependency_links.txt
snmp_simulator.egg-info/entry_points.txt
snmp_simulator.egg-info/not-zip-safe
snmp_simulator.egg-info/requires.txt
snmp_simulator.egg-info/top_level.txt
snmp_simulator/packages/__init__.py
snmp_simulator/packages/lib_config.py
tests/cisco_2801.walk
tests/test_simulator.py