Metadata-Version: 1.1
Name: snmp-simulator
Version: 0.6.0
Summary: A simple SNMP Simulator driven by agent's snmpwalk
Home-page: https://github.com/xeemetric/snmp-simulator
Author: Dmitry Korobitsin
Author-email: korobicin@gmail.com
License: BSD
Platform: Any
Classifier: Development Status :: 5 - Production/Stable
Classifier: Intended Audience :: Developers
Classifier: License :: OSI Approved :: BSD License
Classifier: Natural Language :: English
Classifier: Programming Language :: Python
